{
  "alternateNames": [],
  "ats": {
    "identifier": "gruponoria",
    "provider": "CUSTOM"
  },
  "company_type": "Enterprise",
  "crawler": {
    "seeds": [
      {
        "category": "careers",
        "source": "path-probe",
        "status": "empty",
        "url": "https://gruponoria.com"
      }
    ]
  },
  "description": "Grupo Noria is a Spanish group focused on the distribution of electrical, fluid, and telecommunications materials.",
  "employees_count": null,
  "hq_country": "ES",
  "id": "grupo-noria",
  "industries": [],
  "is_agency": false,
  "is_social_enterprise": false,
  "logoUrl": "https://media.licdn.com/dms/image/v2/D4D0BAQExKE85aBrCfg/company-logo_100_100/B4DZkEQrPsIEAU-/0/1756713104738/global_noria_logo?e=1774483200&v=beta&t=wnjvdX6QXWQkWY8n1-3RoB3u-ab7xiUbf_TWiq8g2pE",
  "name": "Grupo Noria",
  "office_locations": [
    "Barberà del Vallès, Barcelona"
  ],
  "operating_countries": [],
  "remote_policy": "Unknown",
  "updated_at": "2026-03-16T19:18:19.572577Z",
  "verification_level": "verified",
  "visa_sponsorship": null,
  "website": "https://gruponoria.com"
}
