{
  "id": "inzu-group",
  "name": "INZU Group",
  "alternateNames": [],
  "description": "INZU Group is a company profile created during backlog processing.",
  "website": null,
  "logoUrl": "https://media.licdn.com/dms/image/v2/C4D0BAQFG273Y07SEmA/company-logo_100_100/company-logo_100_100/0/1630547899623?e=1774483200&v=beta&t=acjIkS1KDntFZt0cJVTg0UxSRsq1kZFO6RslRep2KLo",
  "industries": [],
  "company_type": "Enterprise",
  "is_agency": false,
  "is_social_enterprise": false,
  "hq_country": "ES",
  "operating_countries": [],
  "office_locations": [],
  "remote_policy": "Unknown",
  "visa_sponsorship": null,
  "employees_count": null,
  "verification_level": "silver",
  "updated_at": "2026-03-10T07:34:10.000729Z",
  "crawler": {
    "seeds": []
  }
}
