{
  "alternateNames": [],
  "ats": {
    "identifier": "brg",
    "provider": "CUSTOM"
  },
  "company_type": "Consultancy",
  "crawler": {
    "seeds": [
      {
        "category": "careers",
        "source": "apply-url-mining",
        "status": "active",
        "url": "https://thinkbrg.wd5.myworkdayjobs.com/BRG_External_Career_Site"
      }
    ]
  },
  "description": "Berkeley Research Group (BRG) is a global consulting firm that helps organizations in the areas of disputes, investigations, and strategy.",
  "employees_count": null,
  "hq_country": "US",
  "id": "brg",
  "industries": [],
  "is_agency": false,
  "is_social_enterprise": false,
  "logoUrl": "https://media.licdn.com/dms/image/v2/D4E0BAQGLz5g3wR955w/company-logo_100_100/company-logo_100_100/0/1719854349434/berkeley_research_group_llc_logo?e=1774483200&v=beta&t=O0yllbVlVk4OcORAJ9kQxiyqQ_kQsDEucZ4TPyCKfIM",
  "name": "BRG",
  "office_locations": [
    "Berkeley"
  ],
  "operating_countries": [],
  "remote_policy": "Unknown",
  "updated_at": "2026-03-16T20:43:50.818992Z",
  "verification_level": "verified",
  "visa_sponsorship": null,
  "website": "https://www.thinkbrg.com"
}
