{
  "alternateNames": [
    "Z Energy"
  ],
  "company_type": "Enterprise",
  "crawler": {
    "seeds": [
      {
        "category": "unknown",
        "url": "http://www.z.co.nz/careers"
      }
    ]
  },
  "description": "Z Energy is Aotearoa's largest transport energy provider, committed to decarbonizing NZ's transport network through fuel today and EV solutions tomorrow.",
  "employees_count": 1000,
  "hq_country": "NZ",
  "id": "z-energy-nz",
  "industries": [
    "Energy",
    "Oil and Gas",
    "Software Development",
    "Sustainability"
  ],
  "is_agency": false,
  "is_social_enterprise": false,
  "logoUrl": "https://media.licdn.com/dms/image/v2/C4D0BAQH9oNG_EcpVEg/company-logo_100_100/company-logo_100_100/0/1631347021725?e=1773878400&v=beta&t=-kxtK3lOAY_REZc-b6IayfW0PliBqNxnDxz3JBfF0lo",
  "name": "Z Energy NZ",
  "office_locations": [
    "Wellington",
    "Auckland"
  ],
  "operating_countries": [
    "NZ"
  ],
  "remote_policy": "Hybrid",
  "updated_at": "2026-03-10T14:00:00Z",
  "verification_level": "silver",
  "visa_sponsorship": {
    "last_verified": null,
    "notes": null,
    "offered": true,
    "source": null,
    "types": []
  },
  "website": "http://www.z.co.nz"
}
