{
  "id": "youshift",
  "name": "YouShift",
  "alternateNames": [],
  "description": "YouShift is a company profile created during backlog processing.",
  "website": null,
  "logoUrl": "https://media.licdn.com/dms/image/v2/D4D0BAQE_shlVS_7EwQ/company-logo_100_100/company-logo_100_100/0/1686911281304/you_shift_logo?e=1774483200&v=beta&t=UDdU1ieOcbMNeC-7hzNVVD5SPnVefkmgo1GOf41G78o",
  "industries": [],
  "company_type": "Startup",
  "is_agency": false,
  "is_social_enterprise": false,
  "hq_country": "AU",
  "operating_countries": [],
  "office_locations": [],
  "remote_policy": "Unknown",
  "visa_sponsorship": null,
  "employees_count": null,
  "verification_level": "silver",
  "updated_at": "2026-03-10T06:38:11.418737Z",
  "crawler": {
    "seeds": []
  }
}
