{
  "alternateNames": [],
  "company_type": "Startup",
  "crawler": {
    "seeds": []
  },
  "description": "DroneDeploy is a company profile created during backlog processing.",
  "employees_count": null,
  "hq_country": "US",
  "id": "dronedeploy",
  "industries": [],
  "is_agency": false,
  "is_social_enterprise": false,
  "logoUrl": "https://media.licdn.com/dms/image/v2/D560BAQESF0Xp13c_Ag/company-logo_100_100/company-logo_100_100/0/1665423654437/dronedeploy_logo?e=1774483200&v=beta&t=TsUMyuTyg1Jj8nFiUe2gQN9IaQPFcI8Kku7LhUVjGtw",
  "name": "DroneDeploy",
  "office_locations": [],
  "operating_countries": [],
  "remote_policy": "Unknown",
  "updated_at": "2026-03-10T06:52:06.145942Z",
  "verification_level": "silver",
  "visa_sponsorship": null,
  "website": null
}
