{
  "id": "hydra-search",
  "name": "Hydra Search",
  "alternateNames": [],
  "description": "Hydra Search is a company profile created during backlog processing.",
  "website": "https://hydrasearch.com.au",
  "logoUrl": "https://media.licdn.com/dms/image/v2/D560BAQG1bbu7nTV96g/company-logo_100_100/company-logo_100_100/0/1710208427840/hydra_search_logo?e=1774483200&v=beta&t=YDx88yzg1S4KmgwwFHd-IOyoPoqEX9yQikS9hcdDqoA",
  "industries": [
    "Software Development"
  ],
  "company_type": "Agency",
  "is_agency": true,
  "is_social_enterprise": false,
  "hq_country": "AU",
  "operating_countries": [],
  "office_locations": [],
  "remote_policy": "Unknown",
  "visa_sponsorship": null,
  "employees_count": null,
  "verification_level": "silver",
  "updated_at": "2026-03-10T03:36:42.903748Z",
  "crawler": {
    "seeds": [
      {
        "url": "https://hydrasearch.com.au/careers",
        "category": "unknown"
      }
    ]
  }
}
