{
  "alternateNames": [],
  "company_type": "Enterprise",
  "crawler": {
    "seeds": []
  },
  "description": "MongoDB is a company profile created during backlog processing.",
  "employees_count": null,
  "hq_country": "US",
  "id": "mongodb",
  "industries": [],
  "is_agency": false,
  "is_social_enterprise": false,
  "logoUrl": "https://media.licdn.com/dms/image/v2/C4D0BAQFKe8PwqzyHyA/company-logo_100_100/company-logo_100_100/0/1635171226992/mongodbinc_logo?e=1774483200&v=beta&t=Ghm-RfHLYhazYVyzejgYr_V18S-CSbQFh0sdOXOSUVA",
  "name": "MongoDB",
  "office_locations": [],
  "operating_countries": [],
  "remote_policy": "Unknown",
  "updated_at": "2026-03-10T06:28:37.674085Z",
  "verification_level": "silver",
  "visa_sponsorship": null,
  "website": null
}
