{
  "alternateNames": [],
  "ats": {
    "identifier": "fusionhit",
    "provider": "SMARTRECRUITERS"
  },
  "company_type": "Consultancy",
  "crawler": {
    "seeds": []
  },
  "description": "FusionHit is a software development outsourcing company providing Agile teams and high-quality software solutions.",
  "employees_count": null,
  "hq_country": "US",
  "id": "fusionhit",
  "industries": [],
  "is_agency": false,
  "is_social_enterprise": false,
  "logoUrl": "https://media.licdn.com/dms/image/v2/C4E0BAQFKAiCy2Fft0Q/company-logo_100_100/company-logo_100_100/0/1633025489433/fusionhit_logo?e=1774483200&v=beta&t=HiERx7oXFgImR7RJuTEoIrKqDKatTGS80jgrP8Z2opQ",
  "name": "FusionHit",
  "office_locations": [
    "San José"
  ],
  "operating_countries": [],
  "remote_policy": "Unknown",
  "updated_at": "2026-03-16T20:25:57.702704Z",
  "verification_level": "verified",
  "visa_sponsorship": null,
  "website": "https://www.fusionhit.com"
}
