{
  "id": "airtificial",
  "name": "AIRTIFICIAL",
  "alternateNames": [],
  "description": "AIRTIFICIAL is a company profile created during backlog processing.",
  "website": null,
  "logoUrl": "https://media.licdn.com/dms/image/v2/D560BAQE3HfN7tMrByg/company-logo_100_100/B56ZYffbEDH0AQ-/0/1744285053582/airtificial_logo?e=1774483200&v=beta&t=cRYtbysVw9MKvSX6bRj0nEnnwaRw2RkdIp9TnOY8XnI",
  "industries": [],
  "company_type": "Enterprise",
  "is_agency": false,
  "is_social_enterprise": false,
  "hq_country": "ES",
  "operating_countries": [],
  "office_locations": [],
  "remote_policy": "Unknown",
  "visa_sponsorship": null,
  "employees_count": null,
  "verification_level": "silver",
  "updated_at": "2026-03-10T07:39:05.140070Z",
  "crawler": {
    "seeds": []
  }
}
