{
  "id": "elcee",
  "name": "ELCEE",
  "alternateNames": [],
  "description": "ELCEE is a company profile created during backlog processing.",
  "website": null,
  "logoUrl": "https://media.licdn.com/dms/image/v2/D4E0BAQH_FACYRxArdw/company-logo_100_100/B4EZfQGXTVGwAY-/0/1751543019116/elcee_logo?e=1774483200&v=beta&t=eU44iYTotllxwzIeE6akaM8xLs6aI2YF12_A0FPc_WI",
  "industries": [],
  "company_type": "Enterprise",
  "is_agency": false,
  "is_social_enterprise": false,
  "hq_country": "NL",
  "operating_countries": [],
  "office_locations": [],
  "remote_policy": "Unknown",
  "visa_sponsorship": null,
  "employees_count": null,
  "verification_level": "silver",
  "updated_at": "2026-03-10T06:57:28.207311Z",
  "crawler": {
    "seeds": []
  }
}
