{
  "alternateNames": [],
  "ats": {
    "identifier": "entelgy",
    "provider": "CUSTOM"
  },
  "company_type": "Unknown",
  "crawler": {
    "seeds": [
      {
        "category": "careers",
        "source": "path-probe",
        "status": "empty",
        "url": "https://entelgy.com/"
      }
    ]
  },
  "description": "Entelgy is a global technology consultancy focused on digital transformation, cybersecurity, and business process automation.",
  "employees_count": null,
  "hq_country": "NZ",
  "id": "entelgy",
  "industries": [],
  "is_agency": false,
  "is_social_enterprise": false,
  "logoUrl": "https://media.licdn.com/dms/image/v2/C4E0BAQHwYHPkCtJXoA/company-logo_100_100/company-logo_100_100/0/1630592569865/entelgy_logo?e=1774483200&v=beta&t=HhnMDRe7N3JyKlohgxQw9Q3VZwEppbM16rSEmamArsc",
  "name": "Entelgy",
  "office_locations": [
    "Madrid"
  ],
  "operating_countries": [],
  "remote_policy": "Unknown",
  "updated_at": "2026-03-16T20:41:54.396126Z",
  "verification_level": "verified",
  "visa_sponsorship": null,
  "website": "https://www.entelgy.com"
}
