{
  "id": "seresco",
  "name": "Seresco",
  "alternateNames": [],
  "description": "Seresco is a company profile created during backlog processing.",
  "website": null,
  "logoUrl": "https://media.licdn.com/dms/image/v2/D4D0BAQGPFr9qzamskw/company-logo_100_100/B4DZahv26.GwAQ-/0/1746470400063/seresco_logo?e=1774483200&v=beta&t=vB-KPqpd28fjZNwGidtWknuuaBy0jelgUPpdZInLwjA",
  "industries": [],
  "company_type": "Consultancy",
  "is_agency": false,
  "is_social_enterprise": false,
  "hq_country": "ES",
  "operating_countries": [],
  "office_locations": [],
  "remote_policy": "Unknown",
  "visa_sponsorship": null,
  "employees_count": null,
  "verification_level": "silver",
  "updated_at": "2026-03-10T07:34:10.000729Z"
}
