{
  "id": "smc-aus-nz",
  "name": "SMC Corporation Australia and New Zealand",
  "alternateNames": [],
  "description": "SMC Corporation Australia and New Zealand is a company profile created during backlog processing.",
  "website": null,
  "logoUrl": "https://media.licdn.com/dms/image/v2/D560BAQEmyIUVu2a27w/company-logo_100_100/B56ZXzgivHGcAU-/0/1743547149800/smc_corporation_australia_new_zealand_group_logo?e=1774483200&v=beta&t=YZ6xsTiEWS3YmeNHI43TrYP2Ypw-QTzcsYH4dFOGWKg",
  "industries": [],
  "company_type": "Enterprise",
  "is_agency": false,
  "is_social_enterprise": false,
  "hq_country": "JP",
  "operating_countries": [],
  "office_locations": [],
  "remote_policy": "Unknown",
  "visa_sponsorship": null,
  "employees_count": null,
  "verification_level": "silver",
  "updated_at": "2026-03-10T07:27:03.818991Z"
}