{
  "alternateNames": [],
  "company_type": "Product",
  "crawler": {
    "seeds": [
      {
        "category": "unknown",
        "url": "https://www.revolut.com/careers"
      }
    ]
  },
  "description": "Revolut is a global financial powerhouse on a mission to deliver total financial freedom through its unified powerhouse of spending, saving, investing, and AI-driven banking products.",
  "employees_count": 10000,
  "hq_country": "GB",
  "id": "revolut",
  "industries": [
    "Fintech",
    "Banking",
    "SaaS",
    "AI"
  ],
  "is_agency": false,
  "is_social_enterprise": false,
  "logoUrl": "https://media.licdn.com/dms/image/v2/D4E0BAQFBudSGoYdD9g/company-logo_100_100/company-logo_100_100/0/1736441557682/revolut_logo?e=1774483200&v=beta&t=g1ogB706z9WicX9uaY4x1RNsa0icRkYymTHmzmMVCD8",
  "name": "Revolut",
  "office_locations": [
    "London",
    "Sydney",
    "Barcelona",
    "Vilnius"
  ],
  "operating_countries": [
    "GB",
    "AU",
    "US",
    "LT",
    "Worldwide"
  ],
  "remote_policy": "Remote",
  "updated_at": "2026-03-10T10:00:00Z",
  "verification_level": "silver",
  "visa_sponsorship": {
    "last_verified": null,
    "notes": null,
    "offered": true,
    "source": null,
    "types": []
  },
  "website": "https://www.revolut.com"
}
