{
  "id": "les-mills-brasil",
  "name": "Les Mills Brasil 🇧🇷",
  "alternateNames": [],
  "description": "A Les Mills oferece experiências fitness que mudam vidas há mais de 50 anos. Agora uma marca fitness internacional, misturamos música, motivação e movimento para milhões de pessoas ao redor do mundo através dos nossos programas mundiais de aulas coletivas. Nossa missão é simples – criar um planeta mais saudável.\n\nNós misturamos os limites das experiências físicas e digitais para oferecer aos nossos parceiros melhores soluções de atividade física. Sinta nosso amor pelo treino coletivo ao vivo com o icônico treino com barra: BODYPUMP.  Pedale pela utopia e distopia, tudo no mesmo treino com a experiência cycle envolvente do THE TRIP. Reserve seu lugar na primeira fila do BODYCOMBAT, aula inspirada em artes marciais ou em qualquer um dos nossos +1000 treinos disponíveis no aplicativo LES MILLS On Demand. \n\nCriar um planeta mais saudável significa mais do que se exercitar. Estamos dedicados à neutralização de carbono, medindo e compensando as emissões de dióxido de carbono para cada um dos nossos escritórios globais. Por meio do nosso programa BORN TO MOVE e da parceria com a UNICEF, estamos unidos em nossa ambição de criar um mundo onde todas as crianças sobrevivam e prosperem. \n\nNosso objetivo é fortalecer ainda mais as forças e permitir que os membros do nosso time joguem o jogo. Diversidade, equidade e inclusão são mentalidade e cultura; um equilíbrio saudável entre trabalho e vida pessoal é essencial e o encorajamento para “exercitar sua paixão” é fundamental.",
  "website": "https://lesmills.com/br/",
  "logoUrl": "https://media.licdn.com/dms/image/v2/C4E0BAQFb633zD6R1Hg/company-logo_100_100/company-logo_100_100/0/1631377419885/les_mills_brasil_fitness_logo?e=1774483200&v=beta&t=hw8V86iU_q6RciARDZGGtUfAYOlMPLSoL3_0GCpFEuY",
  "industries": [
    "Wellness",
    "Fitness Services"
  ],
  "company_type": "Enterprise",
  "is_agency": false,
  "is_social_enterprise": false,
  "hq_country": "NZ",
  "operating_countries": [],
  "office_locations": [],
  "remote_policy": "Unknown",
  "visa_sponsorship": null,
  "employees_count": null,
  "verification_level": "silver",
  "updated_at": "2026-03-10T03:36:42.903748Z",
  "crawler": {
    "seeds": [
      {
        "url": "https://lesmills.com/br/careers",
        "category": "unknown"
      }
    ]
  }
}
