{
  "id": "loanoptions-ai",
  "name": "LoanOptions.ai",
  "alternateNames": [],
  "description": "LoanOptions.ai is a fast-growing startup providing an AI-driven loan brokerage and asset finance software platform to streamline the lending process for consumers and businesses.",
  "website": "https://loanoptions.ai",
  "logoUrl": "https://media.licdn.com/dms/image/v2/D560BAQGwl9_QptcW4w/company-logo_100_100/company-logo_100_100/0/1736985842928/loanoptions_ai_logo?e=1774483200&v=beta&t=mpehVQ2s7wBgM7qEDKbgBjfzB9tWmxzekOPhNm-KLIY",
  "industries": [
    "Fintech",
    "AI",
    "SaaS"
  ],
  "company_type": "Product",
  "is_agency": false,
  "is_social_enterprise": false,
  "hq_country": "AU",
  "operating_countries": [
    "AU"
  ],
  "office_locations": [
    "Sydney"
  ],
  "remote_policy": "On-site",
  "visa_sponsorship": {
    "offered": true,
    "types": [],
    "notes": null,
    "last_verified": null,
    "source": null
  },
  "employees_count": 50,
  "verification_level": "silver",
  "updated_at": "2026-03-10T09:30:00Z"
}