{
  "id": "teamupdraft",
  "name": "TeamUpdraft",
  "alternateNames": [],
  "description": "TeamUpdraft is a company profile created during backlog processing.",
  "website": null,
  "logoUrl": "https://media.licdn.com/dms/image/v2/D4D0BAQG2NzemxC3Ijw/company-logo_100_100/B4DZW0PeNYG8AU-/0/1742485710177/teamupdraft_logo?e=1774483200&v=beta&t=0MlNC7LDajY_bRGIYShbmckujVp1WhcO5q2nEX9n5bI",
  "industries": [],
  "company_type": "Agency",
  "is_agency": true,
  "is_social_enterprise": false,
  "hq_country": "ES",
  "operating_countries": [],
  "office_locations": [],
  "remote_policy": "Unknown",
  "visa_sponsorship": null,
  "employees_count": null,
  "verification_level": "silver",
  "updated_at": "2026-03-10T07:27:03.818991Z",
  "crawler": {
    "seeds": []
  }
}
